prootvec/__init__.py
prootvec/__main__.py
prootvec/losses.py
prootvec/model.py
prootvec/nltp.py
prootvec/reinforce.py
prootvec/tokenizer.py
prootvec/trainer.py
prootvec/trainer_micro.py
prootvec/utils.py
prootvec-0.2.0b2.dist-info/METADATA
prootvec-0.2.0b2.dist-info/WHEEL
prootvec-0.2.0b2.dist-info/top_level.txt
prootvec-0.2.0b2.dist-info/RECORD
