Metadata-Version: 2.4
Name: prootvec
Version: 0.2.0b2
Summary: ProotVec: vectorización y entrenamiento básico en ARM64/Ubuntu/Termux con MLP minimal (micrograd)
Author-email: TuNombre <tucorreo@example.com>
License: MIT
Project-URL: Homepage, https://pypi.org/project/prootvec/
Requires-Python: >=3.8
Requires-Dist: numpy>=1.20
Requires-Dist: regex>=2020.0.0
Requires-Dist: tqdm>=4.60.0
Requires-Dist: micrograd>=0.1.0
